Metadata-Version: 1.0
Name: probability-dist-gb
Version: 0.1
Summary: Gaussian And Binomial distributions
Home-page: UNKNOWN
Author: UNKNOWN
Author-email: UNKNOWN
License: UNKNOWN
Platform: UNKNOWN
